docs/source/conf.py
tangram/__init__.py
tangram/_version.py
tangram/mapping_optimizer.py
tangram/mapping_utils.py
tangram/plot_utils.py
tangram/utils.py
tests/tangram_test.py
tangram_sc-1.0.4.dist-info/LICENSE.md
tangram_sc-1.0.4.dist-info/METADATA
tangram_sc-1.0.4.dist-info/WHEEL
tangram_sc-1.0.4.dist-info/top_level.txt
tangram_sc-1.0.4.dist-info/RECORD
