Metadata-Version: 2.1
Name: tangram-sc
Version: 1.0.4
Summary: Spatial alignment of single cell transcriptomic data.
Home-page: https://github.com/broadinstitute/Tangram
Author: Tommaso Biancalani, Gabriele Scalia
Author-email: tommaso.biancalani@gmail.com
Classifier: Programming Language :: Python :: 3.8
Classifier: Operating System :: MacOS
Requires-Python: >=3.8.5
License-File: LICENSE.md
Requires-Dist: pip
Requires-Dist: torch
Requires-Dist: pandas
Requires-Dist: numpy
Requires-Dist: scipy
Requires-Dist: matplotlib
Requires-Dist: seaborn
Requires-Dist: scanpy
Requires-Dist: scikit-learn
Requires-Dist: tqdm
